zimbraweb/__init__.py
zimbraweb/emlparsing.py
zimbraweb-2.1.1.dist-info/LICENSE
zimbraweb-2.1.1.dist-info/METADATA
zimbraweb-2.1.1.dist-info/WHEEL
zimbraweb-2.1.1.dist-info/top_level.txt
zimbraweb-2.1.1.dist-info/RECORD
