Metadata-Version: 2.1
Name: zimbraweb
Version: 2.1.1
Summary: A Python wrapper for the Zimbra Web Interface
Home-page: https://github.com/TINF21CS1/python-zimbra-web/
Author: Cirosec Studis
License: GPL-3.0
Platform: unix
Platform: linux
Platform: osx
Platform: cygwin
Platform: win32
Classifier: Programming Language :: Python :: 3
Classifier: Programming Language :: Python :: 3 :: Only
Classifier: Programming Language :: Python :: 3.6
Classifier: Programming Language :: Python :: 3.7
Classifier: Programming Language :: Python :: 3.8
Classifier: Programming Language :: Python :: 3.9
Classifier: Programming Language :: Python :: 3.10
Requires-Python: >=3.6
License-File: LICENSE
Requires-Dist: requests (>=2)
Provides-Extra: testing
Requires-Dist: pytest (>=6.0) ; extra == 'testing'
Requires-Dist: pytest-cov (>=2.0) ; extra == 'testing'
Requires-Dist: mypy (>=0.910) ; extra == 'testing'
Requires-Dist: flake8 (>=3.9) ; extra == 'testing'
Requires-Dist: tox (>=3.24) ; extra == 'testing'
Requires-Dist: types-request (>=2.25) ; extra == 'testing'
Requires-Dist: types-setuptools (>=57.4.2) ; extra == 'testing'
Requires-Dist: sphinx (>=4.2) ; extra == 'testing'
